MANIFEST.in
README.md
setup.py
webslides/__init__.py
webslides/main.py
webslides.egg-info/PKG-INFO
webslides.egg-info/SOURCES.txt
webslides.egg-info/dependency_links.txt
webslides.egg-info/requires.txt
webslides.egg-info/top_level.txt
webslides/modules/demo.py
webslides/modules/generate.py
webslides/modules/hello_world.py
webslides/modules/input_validations.py
webslides/modules/other.py
webslides/modules/pagination.py
webslides/modules/tohtml.py
webslides/modules/__pycache__/demo.cpython-311.pyc
webslides/modules/__pycache__/generate.cpython-311.pyc
webslides/modules/__pycache__/input_validations.cpython-311.pyc
webslides/modules/__pycache__/other.cpython-311.pyc
webslides/modules/__pycache__/pagination.cpython-311.pyc
webslides/modules/__pycache__/tohtml.cpython-311.pyc
webslides/static/css/style.css
webslides/static/demodata/df_demo.html
webslides/static/demodata/folium_demo.html