Metadata-Version: 2.1
Name: webslides
Version: 0.7.3
Summary: Creates powerpoint like slides in HTML format. Including title page, index page and page navigation.
Author: Derk-Jan Woltjer
Author-email: derkjan.woltjer@gmail.com
License: MIT License
